{"skeleton":{"hash":"nmoBWtV7c0Y","spine":"4.0.56","x":-102.9,"y":-2.26,"width":197.75,"height":569.27,"fps":60,"images":"./images/","audio":"C:/Users/Utente/Pictures/Exit/Spine/Bimbo/Alieno"},"bones":[{"name":"root","color":"ff0000ff"},{"name":"bone","parent":"root","length":47.2,"rotation":92.15,"x":-5.6,"y":211.06,"color":"ff0000ff"},{"name":"bone2","parent":"bone","length":55.47,"rotation":-4.58,"x":47.2,"color":"ff0000ff"},{"name":"bone3","parent":"bone2","length":53.68,"rotation":0.55,"x":55.47,"color":"ff0000ff"},{"name":"bone4","parent":"bone3","length":36,"rotation":-0.93,"x":53.68,"color":"ff0000ff"},{"name":"bone5","parent":"bone4","length":44.31,"rotation":6.63,"x":38.64,"y":0.72,"color":"ff0000ff"},{"name":"bone6","parent":"bone5","length":15.54,"rotation":0.13,"x":44.3,"y":-0.31,"color":"ff0000ff"},{"name":"bone7","parent":"bone6","x":33.99,"y":-4.49,"color":"ff0000ff"},{"name":"bone8","parent":"bone6","x":35.29,"y":22.22,"color":"ff0000ff"},{"name":"bone9","parent":"bone4","length":35.35,"rotation":96.28,"x":-4.2,"y":24.8,"color":"ff0000ff"},{"name":"bone10","parent":"bone4","length":93.25,"rotation":169.89,"x":-21.84,"y":35.18,"color":"ff0000ff"},{"name":"bone11","parent":"bone10","length":65.01,"rotation":7.26,"x":93.25,"color":"ff0000ff"},{"name":"bone12","parent":"bone11","length":48.13,"rotation":4.39,"x":65.01,"color":"ff0000ff"},{"name":"bone13","parent":"bone4","length":31.12,"rotation":-92.11,"x":-2.68,"y":-38.82,"color":"ff0000ff"},{"name":"bone14","parent":"bone3","length":94.16,"rotation":-167.31,"x":39.27,"y":-42.88,"color":"ff0000ff"},{"name":"bone15","parent":"bone14","length":70.14,"rotation":-7.74,"x":94.16,"color":"ff0000ff"},{"name":"bone16","parent":"bone15","length":51.87,"rotation":-4.24,"x":70.14,"color":"ff0000ff"},{"name":"bone17","parent":"bone","x":-51.18,"y":24.56,"color":"ff0000ff"},{"name":"bone18","parent":"bone17","x":-57.26,"y":13.92,"color":"ff0000ff"},{"name":"bone19","parent":"bone","x":-49.72,"y":-22.04,"color":"ff0000ff"},{"name":"bone20","parent":"bone19","x":-59.76,"y":-10.06,"color":"ff0000ff"},{"name":"bone21","parent":"bone","length":87.72,"rotation":176.11,"x":-43.47,"y":16.24,"color":"ff0000ff"},{"name":"bone22","parent":"bone21","length":73.79,"rotation":0.92,"x":87.72,"color":"ff0000ff"},{"name":"bone23","parent":"bone","length":95.77,"rotation":-179.91,"x":-42.41,"y":-12.69,"color":"ff0000ff"},{"name":"bone24","parent":"bone23","length":66.31,"rotation":-0.85,"x":95.77,"color":"ff0000ff"},{"name":"ikr","parent":"root","x":14.01,"y":7.16,"color":"ff0000ff"},{"name":"ikl","parent":"root","x":-23.94,"y":5.56,"color":"ff0000ff"}],"slots":[{"name":"Spalla","bone":"root","attachment":"Spalla"},{"name":"Spalla2","bone":"root","attachment":"Spalla"},{"name":"avabracio","bone":"root","attachment":"avabracio"},{"name":"avabracio2","bone":"root","attachment":"avabracio"},{"name":"bacino","bone":"root","attachment":"bacino"},{"name":"gambaup","bone":"root","attachment":"gambaup"},{"name":"gambaup2","bone":"root","attachment":"gambaup"},{"name":"gambagiu","bone":"root","attachment":"gambagiu"},{"name":"gambagiu2","bone":"root","attachment":"gambagiu"},{"name":"collo","bone":"root","attachment":"collo"},{"name":"piede","bone":"root","attachment":"piede"},{"name":"piede2","bone":"root","attachment":"piede"},{"name":"body","bone":"root","attachment":"body"},{"name":"spallacc","bone":"root","attachment":"spallacc"},{"name":"spallacc2","bone":"root","attachment":"spallacc"},{"name":"testa","bone":"root","attachment":"testa"},{"name":"mano","bone":"root","attachment":"mano"},{"name":"mano2","bone":"root","attachment":"mano"},{"name":"Eye","bone":"root","attachment":"Eye"},{"name":"Eye2","bone":"root","attachment":"Eye"}],"ik":[{"name":"ikl","order":1,"bones":["bone21","bone22"],"target":"ikl"},{"name":"ikr","bones":["bone23","bone24"],"target":"ikr"}],"skins":[{"name":"default","attachments":{"avabracio":{"avabracio":{"type":"mesh","uvs":[1,0.14529,1,0.31073,1,0.5297,1,0.75841,1,1,0,1,0,0.73894,0,0.49564,0,0.2864,0,0.11609,0,0,1,0],"triangles":[9,10,11,9,11,0,8,9,0,8,0,1,7,8,1,7,1,2,6,7,2,6,2,3,5,6,3,5,3,4],"vertices":[1,10,62.61,4.67,1,2,11,-8.4,10.63,0.11001,10,83.57,9.48,0.88999,1,11,19.93,13.43,1,1,11,49.51,16.37,1,1,11,80.77,19.47,1,1,11,84.32,-16.36,1,1,11,50.55,-19.71,1,2,11,19.07,-22.83,0.97058,10,115.05,-20.23,0.02942,2,11,-7.99,-25.51,0.26363,10,88.54,-26.32,0.73637,2,11,-30.03,-27.7,0.00477,10,66.96,-31.27,0.99523,1,10,52.25,-34.64,1,1,10,44.2,0.45,1],"hull":12,"edges":[8,10,20,22,18,20,0,22,18,0,16,18,0,2,16,2,14,16,2,4,14,4,10,12,12,14,4,6,6,8,12,6],"width":36,"height":130}},"avabracio2":{"avabracio":{"type":"mesh","uvs":[1,0.14529,1,0.31073,1,0.5297,1,0.75841,1,1,0,1,0,0.73894,0,0.49564,0,0.2864,0,0.11609,0,0,1,0],"triangles":[9,10,11,9,11,0,8,9,0,8,0,1,7,8,1,7,1,2,6,7,2,6,2,3,5,6,3,5,3,4],"vertices":[1,14,66.43,-5.84,1,2,15,-5.21,-10.67,0.10063,14,87.55,-9.87,0.89937,1,15,23.21,-12.19,1,1,15,52.9,-13.78,1,1,15,84.26,-15.45,1,1,15,86.18,20.5,1,1,15,52.29,22.31,1,2,15,20.71,23.99,0.94919,14,117.91,20.99,0.05081,2,15,-6.45,25.45,0.24326,14,91.19,26.08,0.75674,2,15,-28.56,26.63,0.00162,14,69.44,30.23,0.99838,1,14,54.62,33.06,1,1,14,47.87,-2.3,1],"hull":12,"edges":[8,10,20,22,18,20,0,22,18,0,16,18,0,2,16,2,14,16,2,4,14,4,10,12,12,14,4,6,6,8,12,6],"width":36,"height":130}},"bacino":{"bacino":{"x":-1.9,"y":176.02,"width":80,"height":58}},"body":{"body":{"type":"mesh","uvs":[1,0.16815,1,0.41145,1,0.65475,1,0.82776,1,1,0.44185,1,0,1,0,0.83677,0,0.66916,0,0.43127,0,0.215,0,0,0.45463,0,1,0,0.44571,0.69798,0.44868,0.46551,0.44354,0.86741,0.45169,0.22939],"triangles":[5,16,4,16,3,4,16,14,3,14,2,3,5,6,16,6,7,16,16,7,14,7,8,14,2,14,15,14,8,15,8,9,15,15,1,2,1,15,17,15,9,17,9,10,17,17,0,1,0,17,12,17,10,12,10,11,12,12,13,0],"vertices":[3,4,3.28,-52.25,0.44881,3,56.11,-52.29,0.51823,2,112.08,-51.75,0.03297,5,4,-82.01,-56.44,0,3,-29.24,-55.11,0.09796,2,26.75,-55.38,0.64718,1,69.44,-57.35,0.24496,19,119.15,-35.3,0.0099,5,4,-167.31,-60.64,0,2,-58.57,-59.01,0.00497,1,-15.9,-54.14,0.4507,19,33.82,-32.1,0.54407,20,93.58,-22.04,2.5E-4,3,1,-76.59,-51.87,2.8E-4,19,-26.87,-29.83,0.57663,20,32.89,-19.76,0.42308,3,4,-288.35,-66.59,0,18,-28.56,-88.08,7.3E-4,20,-27.52,-17.5,0.99927,5,4,-291.06,-11.4,0,17,-83.75,-18.94,6.8E-4,18,-26.49,-32.86,0.52661,19,-85.21,27.66,2.2E-4,20,-25.45,37.72,0.47249,2,18,-24.85,10.85,0.98161,20,-23.81,81.43,0.01839,4,4,-235.99,35.11,0,17,-24.86,22.62,0.58543,18,32.4,8.71,0.41287,20,33.44,79.29,0.0017,2,1,-17.25,44.98,0.49241,17,33.93,20.42,0.50759,4,3,-39.46,43.61,0.1211,2,15.59,43.23,0.63962,1,66.19,41.85,0.23847,17,117.37,17.29,8.2E-4,3,4,-18.01,45.83,0.20872,3,36.41,46.11,0.78796,2,91.43,46.46,0.00332,2,4,57.37,49.53,0.99901,3,111.84,48.6,9.9E-4,1,4,59.58,4.58,1,2,4,62.23,-49.35,0.99979,3,115.1,-50.35,2.1E-4,3,1,-29.01,1.26,0.39976,17,22.17,-23.3,0.29633,19,20.71,23.3,0.30391,3,4,-103.65,-2.86,0,2,5.48,-1.66,0.99962,19,102.24,19.95,3.8E-4,4,17,-37.25,-20.85,0.23456,18,20.01,-34.77,0.30536,19,-38.71,25.75,0.17256,20,21.05,35.81,0.28752,1,3,32.84,1.25,1],"hull":14,"edges":[22,24,24,26,8,10,10,12,16,28,28,4,4,2,30,28,2,30,16,18,30,18,12,14,14,16,10,32,32,28,14,32,4,6,6,8,32,6,2,0,0,26,24,34,34,30,0,34,18,20,20,22,34,20],"width":99,"height":351}},"collo":{"collo":{"type":"mesh","uvs":[1,0.28114,1,0.54899,1,0.79404,1,1,0,1,0,0.76554,0,0.56038,0,0.29823,0,0,1,0],"triangles":[5,6,1,5,1,2,4,5,2,4,2,3,8,9,0,7,8,0,7,0,1,6,7,1],"vertices":[2,5,32.21,-41.4,0.76537,4,75.42,-36.68,0.23463,2,5,2.54,-39.42,0.2131,4,45.72,-38.14,0.7869,2,5,-24.6,-37.61,2.9E-4,4,18.55,-39.48,0.99971,1,4,-4.28,-40.6,1,2,5,-42.42,38.74,0.09184,4,-7.96,34.31,0.90816,2,5,-16.45,37.01,0.3689,4,18.03,35.58,0.6311,2,5,6.27,35.5,0.87592,4,40.77,36.7,0.12408,1,5,35.3,33.56,1,1,5,68.34,31.36,1,2,5,63.35,-43.48,0.95465,4,106.59,-35.15,0.04535],"hull":10,"edges":[6,8,16,18,14,16,0,18,14,0,12,14,0,2,12,2,8,10,10,12,2,4,4,6,10,4],"width":75,"height":111}},"Eye":{"Eye":{"type":"mesh","uvs":[1,0.29949,1,0.66476,1,1,0,1,0,0.67165,0,0.30638,0,0,1,0],"triangles":[6,7,0,5,6,0,5,0,1,4,5,1,2,3,4,2,4,1],"vertices":[1,8,6.49,-7.86,1,1,8,-5.9,-7,1,1,8,-17.27,-6.22,1,1,8,-16.24,8.74,1,1,8,-5.11,7.98,1,1,8,7.28,7.12,1,1,8,17.68,6.4,1,1,8,16.64,-8.56,1],"hull":8,"edges":[4,6,12,14,10,12,0,14,10,0,6,8,8,10,0,2,2,4,8,2],"width":15,"height":34}},"Eye2":{"Eye":{"type":"mesh","uvs":[1,0.29949,1,0.66476,1,1,0,1,0,0.67165,0,0.30638,0,0,1,0],"triangles":[6,7,0,5,6,0,5,0,1,4,5,1,2,3,4,2,4,1],"vertices":[1,7,5.92,-8.24,1,1,7,-6.47,-7.39,1,1,7,-17.84,-6.6,1,1,7,-16.8,8.36,1,1,7,-5.67,7.6,1,1,7,6.72,6.74,1,1,7,17.11,6.02,1,1,7,16.08,-8.94,1],"hull":8,"edges":[4,6,12,14,10,12,0,14,10,0,6,8,8,10,0,2,2,4,8,2],"width":15,"height":34}},"gambagiu":{"gambagiu":{"type":"mesh","color":"858585ff","uvs":[1,0.24291,1,0.52711,1,0.82965,1,1,0,1,0,0.81131,0,0.49961,0,0.24291,0,0,1,0],"triangles":[7,8,9,7,9,0,6,7,0,6,0,1,5,6,1,5,1,2,4,5,2,4,2,3],"vertices":[1,22,12.84,17.17,1,1,22,32.44,17.45,1,1,22,53.32,17.75,1,1,22,65.07,17.92,1,1,22,65.58,-17.07,1,1,22,52.56,-17.26,1,1,22,31.05,-17.57,1,1,22,13.34,-17.83,1,1,22,-3.42,-18.07,1,1,22,-3.92,16.92,1],"hull":10,"edges":[6,8,16,18,14,16,0,18,14,0,0,2,12,14,2,12,8,10,10,12,2,4,4,6,10,4],"width":35,"height":69}},"gambagiu2":{"gambagiu":{"type":"mesh","uvs":[1,0.24291,1,0.52711,1,0.82965,1,1,0,1,0,0.81131,0,0.49961,0,0.24291,0,0,1,0],"triangles":[7,8,9,7,9,0,6,7,0,6,0,1,5,6,1,5,1,2,4,5,2,4,2,3],"vertices":[1,24,7.71,20.81,1,1,24,27.31,20.33,1,1,24,48.18,19.83,1,1,24,59.93,19.54,1,1,24,59.08,-15.44,1,1,24,46.07,-15.13,1,1,24,24.57,-14.61,1,1,24,6.86,-14.18,1,1,24,-9.9,-13.78,1,1,24,-9.05,21.21,1],"hull":10,"edges":[6,8,16,18,14,16,0,18,14,0,0,2,12,14,2,12,8,10,10,12,2,4,4,6,10,4],"width":35,"height":69}},"gambaup":{"gambaup":{"type":"mesh","color":"858585ff","uvs":[1,0.1261,1,0.31724,1,0.47198,1,0.69042,1,0.87246,1,1,0,1,0,0.86791,0,0.69497,0,0.46743,0,0.30359,0,0.14431,0,0,1,0],"triangles":[12,13,0,11,12,0,1,10,11,1,11,0,9,10,1,9,1,2,9,2,3,8,9,3,4,7,8,4,8,3,6,7,4,6,4,5],"vertices":[1,21,-12.87,12.92,1,1,21,13.68,13.73,1,1,21,35.18,14.38,1,1,21,65.53,15.31,1,1,21,90.82,16.08,1,1,21,108.54,16.62,1,1,21,109.7,-21.36,1,1,21,91.35,-21.92,1,1,21,67.32,-22.65,1,1,21,35.71,-23.62,1,1,21,12.95,-24.31,1,1,21,-9.18,-24.99,1,1,21,-29.23,-25.6,1,1,21,-30.39,12.39,1],"hull":14,"edges":[10,12,24,26,22,24,0,26,22,0,20,22,0,2,20,2,18,20,2,4,18,4,16,18,4,6,16,6,6,8,8,10,12,14,14,16,8,14],"width":38,"height":139}},"gambaup2":{"gambaup":{"type":"mesh","uvs":[1,0.1261,1,0.31724,1,0.47198,1,0.69042,1,0.87246,1,1,0,1,0,0.86791,0,0.69497,0,0.46743,0,0.30359,0,0.14431,0,0,1,0],"triangles":[12,13,0,11,12,0,1,10,11,1,11,0,9,10,1,9,1,2,9,2,3,8,9,3,4,7,8,4,8,3,6,7,4,6,4,5],"vertices":[1,23,-9.4,24.12,1,1,23,17.15,23.08,1,1,23,38.64,22.24,1,1,23,68.98,21.05,1,1,23,94.27,20.06,1,1,23,111.98,19.37,1,1,23,110.5,-18.6,1,1,23,92.15,-17.88,1,1,23,68.13,-16.94,1,1,23,36.52,-15.71,1,1,23,13.77,-14.82,1,1,23,-8.35,-13.95,1,1,23,-28.4,-13.17,1,1,23,-26.91,24.8,1],"hull":14,"edges":[10,12,24,26,22,24,0,26,22,0,20,22,0,2,20,2,18,20,2,4,18,4,16,18,4,6,16,6,6,8,8,10,12,14,14,16,8,14],"width":38,"height":139}},"mano":{"mano":{"type":"mesh","uvs":[1,0.23115,1,0.48536,1,0.76323,1,1,0,1,0,0.76914,0,0.47945,0,0.19568,0,0,1,0],"triangles":[7,8,9,7,9,0,6,7,0,6,0,1,6,1,2,5,6,2,3,4,5,3,5,2],"vertices":[1,12,7.65,31,1,1,12,34.85,31.6,1,1,12,64.57,32.26,1,1,12,89.9,32.82,1,1,12,91.39,-34.16,1,1,12,66.69,-34.71,1,1,12,35.7,-35.4,1,1,12,5.35,-36.07,1,1,12,-15.59,-36.54,1,1,12,-17.08,30.45,1],"hull":10,"edges":[6,8,16,18,14,16,0,18,14,0,12,14,0,2,12,2,8,10,10,12,2,4,4,6,10,4],"width":67,"height":107}},"mano2":{"mano":{"type":"mesh","uvs":[1,0.23115,1,0.48536,1,0.76323,1,1,0,1,0,0.76914,0,0.47945,0,0.19568,0,0,1,0],"triangles":[7,8,9,7,9,0,6,7,0,6,0,1,6,1,2,5,6,2,3,4,5,3,5,2],"vertices":[1,16,6.34,-32.55,1,1,16,33.53,-31.99,1,1,16,63.26,-31.38,1,1,16,88.59,-30.86,1,1,16,87.21,36.13,1,1,16,62.51,35.62,1,1,16,31.52,34.98,1,1,16,1.16,34.35,1,1,16,-19.77,33.92,1,1,16,-18.39,-33.06,1],"hull":10,"edges":[6,8,16,18,14,16,0,18,14,0,12,14,0,2,12,2,8,10,10,12,2,4,4,6,10,4],"width":67,"height":107}},"piede":{"piede":{"type":"mesh","color":"858585ff","uvs":[1,0.57831,1,1,0,1,0,0.47006,0,0,1,0],"triangles":[3,4,5,3,5,0,2,3,0,2,0,1],"vertices":[1,22,67.11,20.95,1,1,22,81.02,21.16,1,1,22,81.57,-16.84,1,1,22,64.09,-17.09,1,1,22,48.58,-17.32,1,1,22,48.03,20.68,1],"hull":6,"edges":[2,4,8,10,4,6,6,8,2,0,0,10,6,0],"width":38,"height":33}},"piede2":{"piede":{"type":"mesh","uvs":[1,0.57831,1,1,0,1,0,0.47006,0,0,1,0],"triangles":[3,4,5,3,5,0,2,3,0,2,0,1],"vertices":[1,24,62.09,22.49,1,1,24,76,22.16,1,1,24,75.08,-15.83,1,1,24,57.6,-15.41,1,1,24,42.09,-15.03,1,1,24,43.01,22.96,1],"hull":6,"edges":[2,4,8,10,4,6,6,8,2,0,0,10,6,0],"width":38,"height":33}},"Spalla":{"Spalla":{"type":"mesh","uvs":[1,0.18793,1,0.39388,1,0.59003,1,0.78128,1,1,0,1,0,0.78128,0,0.59003,0,0.37917,0,0.17812,0,0,1,0],"triangles":[9,10,11,9,11,0,8,9,0,8,0,1,7,8,1,7,1,2,6,7,2,6,2,3,5,6,3,5,3,4],"vertices":[1,10,-14.39,6.5,1,1,10,11.5,12.44,1,1,10,36.16,18.1,1,1,10,60.21,23.61,1,1,10,87.71,29.92,1,1,10,95.98,-6.14,1,1,10,68.48,-12.45,1,1,10,44.44,-17.97,1,1,10,17.93,-24.05,1,1,10,-7.35,-29.85,1,1,10,-29.75,-34.99,1,1,10,-38.02,1.08,1],"hull":12,"edges":[8,10,20,22,18,20,0,22,18,0,16,18,0,2,16,2,2,4,14,16,4,14,10,12,12,14,4,6,6,8,12,6],"width":37,"height":129}},"Spalla2":{"Spalla":{"type":"mesh","uvs":[1,0.18793,1,0.39388,1,0.59003,1,0.78128,1,1,0,1,0,0.78128,0,0.59003,0,0.37917,0,0.17812,0,0,1,0],"triangles":[9,10,11,9,11,0,8,9,0,8,0,1,7,8,1,7,1,2,6,7,2,6,2,3,5,6,3,5,3,4],"vertices":[1,14,-9.79,-7.01,1,1,14,16.31,-11.99,1,1,14,41.17,-16.73,1,1,14,65.4,-21.35,1,1,14,93.11,-26.64,1,1,14,100.05,9.7,1,1,14,72.33,14.99,1,1,14,48.1,19.61,1,1,14,21.38,24.71,1,1,14,-4.1,29.57,1,1,14,-26.67,33.88,1,1,14,-33.6,-2.47,1],"hull":12,"edges":[8,10,20,22,18,20,0,22,18,0,16,18,0,2,16,2,2,4,14,16,4,14,10,12,12,14,4,6,6,8,12,6],"width":37,"height":129}},"spallacc":{"spallacc":{"type":"mesh","uvs":[1,1,0.48201,1,0,1,0,0,0.47071,0,1,0],"triangles":[2,3,4,1,4,5,2,4,1,1,5,0],"vertices":[1,9,-8.08,20.82,1,1,9,20.87,19.06,1,1,9,47.82,17.43,1,1,9,45.64,-18.51,1,1,9,19.33,-16.91,1,1,9,-10.26,-15.12,1],"hull":6,"edges":[4,6,0,10,6,8,8,10,0,2,2,4,8,2],"width":56,"height":36}},"spallacc2":{"spallacc":{"type":"mesh","uvs":[1,1,0.48201,1,0,1,0,0,0.47071,0,1,0],"triangles":[2,3,4,1,4,5,2,4,1,1,5,0],"vertices":[1,13,-10.05,-19.62,1,1,13,18.85,-17.13,1,1,13,45.74,-14.81,1,1,13,42.65,21.06,1,1,13,16.39,18.79,1,1,13,-13.14,16.25,1],"hull":6,"edges":[4,6,0,10,6,8,8,10,0,2,2,4,8,2],"width":56,"height":36}},"testa":{"testa":{"type":"mesh","uvs":[1,1,0,1,0,0,1,0,0.40105,0.555],"triangles":[4,2,3,1,2,4,4,3,0,1,4,0],"vertices":[1,6,-52.47,-61.34,1,1,6,-43.52,68.35,1,1,6,121.08,57,1,1,6,112.14,-72.69,1,1,6,26.14,11.29,1],"hull":4,"edges":[0,2,2,4,4,6,0,6,4,8,8,2,8,6,8,0],"width":130,"height":165}}}}],"animations":{"give hand":{"bones":{"root":{"rotate":[{}],"translate":[{}],"scale":[{}],"shear":[{}]},"bone":{"rotate":[{}],"translate":[{}],"scale":[{}],"shear":[{}]},"bone2":{"rotate":[{}],"translate":[{}],"scale":[{}],"shear":[{}]},"bone3":{"rotate":[{}],"translate":[{}],"scale":[{}],"shear":[{}]},"bone4":{"rotate":[{}],"translate":[{}],"scale":[{}],"shear":[{}]},"bone5":{"rotate":[{"value":22.11}],"translate":[{}],"scale":[{}],"shear":[{}]},"bone6":{"rotate":[{"value":0.66}],"translate":[{}],"scale":[{}],"shear":[{}]},"bone7":{"rotate":[{}],"translate":[{}],"scale":[{}],"shear":[{}]},"bone8":{"rotate":[{}],"translate":[{}],"scale":[{}],"shear":[{}]},"bone9":{"rotate":[{}],"translate":[{}],"scale":[{}],"shear":[{}]},"bone10":{"rotate":[{}],"translate":[{}],"scale":[{}],"shear":[{}]},"bone11":{"rotate":[{"value":-53.62}],"translate":[{}],"scale":[{}],"shear":[{}]},"bone12":{"rotate":[{"value":-65.16}],"translate":[{"x":4.53,"y":8.03}],"scale":[{}],"shear":[{}]},"bone13":{"rotate":[{}],"translate":[{}],"scale":[{}],"shear":[{}]},"bone14":{"rotate":[{}],"translate":[{}],"scale":[{}],"shear":[{}]},"bone15":{"rotate":[{}],"translate":[{}],"scale":[{}],"shear":[{}]},"bone16":{"rotate":[{}],"translate":[{}],"scale":[{}],"shear":[{}]},"bone17":{"rotate":[{}],"translate":[{}],"scale":[{}],"shear":[{}]},"bone18":{"rotate":[{}],"translate":[{}],"scale":[{}],"shear":[{}]},"bone19":{"rotate":[{}],"translate":[{}],"scale":[{}],"shear":[{}]},"bone20":{"rotate":[{}],"translate":[{}],"scale":[{}],"shear":[{}]},"bone21":{"rotate":[{}],"translate":[{}],"scale":[{}],"shear":[{}]},"bone22":{"rotate":[{}],"translate":[{}],"scale":[{}],"shear":[{}]},"bone23":{"rotate":[{"value":-0.7}],"translate":[{}],"scale":[{}],"shear":[{}]},"bone24":{"rotate":[{"value":1.71}],"translate":[{}],"scale":[{}],"shear":[{}]},"ikr":{"rotate":[{}],"translate":[{}],"scale":[{}],"shear":[{}]},"ikl":{"rotate":[{}],"translate":[{}],"scale":[{}],"shear":[{}]}}},"goahead":{"bones":{"root":{"rotate":[{"curve":"stepped"},{"time":0.6667,"curve":"stepped"},{"time":1.1667,"curve":"stepped"},{"time":2.1667,"curve":"stepped"},{"time":2.6667}],"translate":[{"curve":"stepped"},{"time":0.6667,"curve":"stepped"},{"time":1.1667,"curve":"stepped"},{"time":2.1667,"curve":"stepped"},{"time":2.6667}],"scale":[{"curve":"stepped"},{"time":0.6667,"curve":"stepped"},{"time":1.1667,"curve":"stepped"},{"time":2.1667,"curve":"stepped"},{"time":2.6667}],"shear":[{"curve":"stepped"},{"time":0.6667,"curve":"stepped"},{"time":1.1667,"curve":"stepped"},{"time":2.1667,"curve":"stepped"},{"time":2.6667}]},"bone":{"rotate":[{"curve":"stepped"},{"time":0.6667,"curve":"stepped"},{"time":1.1667,"curve":"stepped"},{"time":2.1667,"curve":"stepped"},{"time":2.6667}],"translate":[{"curve":"stepped"},{"time":0.6667,"curve":"stepped"},{"time":1.1667,"curve":"stepped"},{"time":2.1667,"curve":"stepped"},{"time":2.6667}],"scale":[{"curve":"stepped"},{"time":0.6667,"curve":"stepped"},{"time":1.1667,"curve":"stepped"},{"time":2.1667,"curve":"stepped"},{"time":2.6667}],"shear":[{"curve":"stepped"},{"time":0.6667,"curve":"stepped"},{"time":1.1667,"curve":"stepped"},{"time":2.1667,"curve":"stepped"},{"time":2.6667}]},"bone2":{"rotate":[{"curve":"stepped"},{"time":0.6667,"curve":"stepped"},{"time":1.1667,"curve":"stepped"},{"time":2.1667,"curve":"stepped"},{"time":2.6667}],"translate":[{"curve":"stepped"},{"time":0.6667,"curve":"stepped"},{"time":1.1667,"curve":"stepped"},{"time":2.1667,"curve":"stepped"},{"time":2.6667}],"scale":[{"curve":"stepped"},{"time":0.6667,"curve":"stepped"},{"time":1.1667,"curve":"stepped"},{"time":2.1667,"curve":"stepped"},{"time":2.6667}],"shear":[{"curve":"stepped"},{"time":0.6667,"curve":"stepped"},{"time":1.1667,"curve":"stepped"},{"time":2.1667,"curve":"stepped"},{"time":2.6667}]},"bone3":{"rotate":[{"curve":"stepped"},{"time":0.6667,"curve":"stepped"},{"time":1.1667,"curve":"stepped"},{"time":2.1667,"curve":"stepped"},{"time":2.6667}],"translate":[{"curve":[0.222,0,0.444,-22.58,0.222,0,0.444,13.08]},{"time":0.6667,"x":-22.58,"y":13.08,"curve":[0.833,-22.58,1,0,0.833,13.08,1,0]},{"time":1.1667,"curve":[1.25,0,1.458,11.39,1.25,0,1.458,0.11]},{"time":1.6667,"x":11.39,"y":0.11,"curve":[1.875,11.39,2.083,0,1.875,0.11,2.083,0]},{"time":2.1667,"curve":"stepped"},{"time":2.6667}],"scale":[{"curve":"stepped"},{"time":0.6667,"curve":"stepped"},{"time":1.1667,"curve":"stepped"},{"time":2.1667,"curve":"stepped"},{"time":2.6667}],"shear":[{"curve":"stepped"},{"time":0.6667,"curve":"stepped"},{"time":1.1667,"curve":"stepped"},{"time":2.1667,"curve":"stepped"},{"time":2.6667}]},"bone4":{"rotate":[{"curve":"stepped"},{"time":0.6667,"curve":"stepped"},{"time":1.1667,"curve":"stepped"},{"time":2.1667,"curve":"stepped"},{"time":2.6667}],"translate":[{"curve":"stepped"},{"time":0.6667,"curve":"stepped"},{"time":1.1667,"curve":"stepped"},{"time":2.1667,"curve":"stepped"},{"time":2.6667}],"scale":[{"curve":"stepped"},{"time":0.6667,"curve":"stepped"},{"time":1.1667,"curve":"stepped"},{"time":2.1667,"curve":"stepped"},{"time":2.6667}],"shear":[{"curve":"stepped"},{"time":0.6667,"curve":"stepped"},{"time":1.1667,"curve":"stepped"},{"time":2.1667,"curve":"stepped"},{"time":2.6667}]},"bone5":{"rotate":[{"curve":"stepped"},{"time":0.6667,"curve":"stepped"},{"time":1.1667,"curve":"stepped"},{"time":2.1667,"curve":"stepped"},{"time":2.6667}],"translate":[{"curve":"stepped"},{"time":0.6667,"curve":"stepped"},{"time":1.1667,"curve":"stepped"},{"time":2.1667,"curve":"stepped"},{"time":2.6667}],"scale":[{"curve":"stepped"},{"time":0.6667,"curve":"stepped"},{"time":1.1667,"curve":"stepped"},{"time":2.1667,"curve":"stepped"},{"time":2.6667}],"shear":[{"curve":"stepped"},{"time":0.6667,"curve":"stepped"},{"time":1.1667,"curve":"stepped"},{"time":2.1667,"curve":"stepped"},{"time":2.6667}]},"bone6":{"rotate":[{"curve":"stepped"},{"time":0.6667,"curve":"stepped"},{"time":1.1667,"curve":"stepped"},{"time":2.1667,"curve":"stepped"},{"time":2.6667}],"translate":[{"curve":"stepped"},{"time":0.6667,"curve":"stepped"},{"time":1.1667,"curve":"stepped"},{"time":2.1667,"curve":"stepped"},{"time":2.6667}],"scale":[{"curve":"stepped"},{"time":0.6667,"curve":"stepped"},{"time":1.1667,"curve":"stepped"},{"time":2.1667,"curve":"stepped"},{"time":2.6667}],"shear":[{"curve":"stepped"},{"time":0.6667,"curve":"stepped"},{"time":1.1667,"curve":"stepped"},{"time":2.1667,"curve":"stepped"},{"time":2.6667}]},"bone7":{"rotate":[{"curve":"stepped"},{"time":0.6667,"curve":"stepped"},{"time":1.1667,"curve":"stepped"},{"time":2.1667,"curve":"stepped"},{"time":2.6667}],"translate":[{"curve":"stepped"},{"time":0.6667,"curve":"stepped"},{"time":1.1667,"curve":"stepped"},{"time":2.1667,"curve":"stepped"},{"time":2.6667}],"scale":[{"curve":"stepped"},{"time":0.6667,"curve":"stepped"},{"time":1.1667,"curve":"stepped"},{"time":1.6333,"curve":[1.645,1,1.656,0.391,1.645,1,1.656,1]},{"time":1.6667,"x":0.391,"curve":[1.678,0.391,1.689,1,1.678,1,1.689,1]},{"time":1.7,"curve":"stepped"},{"time":2.1667,"curve":"stepped"},{"time":2.6667}],"shear":[{"curve":"stepped"},{"time":0.6667,"curve":"stepped"},{"time":1.1667,"curve":"stepped"},{"time":2.1667,"curve":"stepped"},{"time":2.6667}]},"bone8":{"rotate":[{"curve":"stepped"},{"time":0.6667,"curve":"stepped"},{"time":1.1667,"curve":"stepped"},{"time":2.1667,"curve":"stepped"},{"time":2.6667}],"translate":[{"curve":"stepped"},{"time":0.6667,"curve":"stepped"},{"time":1.1667,"curve":"stepped"},{"time":2.1667,"curve":"stepped"},{"time":2.6667}],"scale":[{"curve":"stepped"},{"time":0.6667,"curve":"stepped"},{"time":1.1667,"curve":"stepped"},{"time":1.6333,"curve":[1.645,1,1.656,0.391,1.645,1,1.656,1]},{"time":1.6667,"x":0.391,"curve":[1.678,0.391,1.689,1,1.678,1,1.689,1]},{"time":1.7,"curve":"stepped"},{"time":2.1667,"curve":"stepped"},{"time":2.6667}],"shear":[{"curve":"stepped"},{"time":0.6667,"curve":"stepped"},{"time":1.1667,"curve":"stepped"},{"time":2.1667,"curve":"stepped"},{"time":2.6667}]},"bone9":{"rotate":[{"curve":"stepped"},{"time":0.6667,"curve":"stepped"},{"time":1.1667,"curve":"stepped"},{"time":2.1667,"curve":"stepped"},{"time":2.6667}],"translate":[{"curve":"stepped"},{"time":0.6667,"curve":"stepped"},{"time":1.1667,"curve":"stepped"},{"time":2.1667,"curve":"stepped"},{"time":2.6667}],"scale":[{"curve":"stepped"},{"time":0.6667,"curve":"stepped"},{"time":1.1667,"curve":"stepped"},{"time":2.1667,"curve":"stepped"},{"time":2.6667}],"shear":[{"curve":"stepped"},{"time":0.6667,"curve":"stepped"},{"time":1.1667,"curve":"stepped"},{"time":2.1667,"curve":"stepped"},{"time":2.6667}]},"bone10":{"rotate":[{"curve":[0.222,0,0.444,-52.96]},{"time":0.6667,"value":-69.19,"curve":[0.833,-81.36,1,-85.19]},{"time":1.1667,"value":-85.19,"curve":"stepped"},{"time":2.1667,"value":-85.19,"curve":[2.333,-85.19,2.5,0]},{"time":2.6667}],"translate":[{"curve":"stepped"},{"time":0.6667,"curve":"stepped"},{"time":1.1667,"curve":"stepped"},{"time":2.1667,"curve":"stepped"},{"time":2.6667}],"scale":[{"curve":"stepped"},{"time":0.6667,"curve":"stepped"},{"time":1.1667,"curve":"stepped"},{"time":2.1667,"curve":"stepped"},{"time":2.6667}],"shear":[{"curve":"stepped"},{"time":0.6667,"curve":"stepped"},{"time":1.1667,"curve":"stepped"},{"time":2.1667,"curve":"stepped"},{"time":2.6667}]},"bone11":{"rotate":[{"curve":[0.222,0,0.444,-94.44]},{"time":0.6667,"value":-94.44,"curve":[0.833,-94.44,1,-16.5]},{"time":1.1667,"value":-8.25,"curve":[1.333,0,2,-16.5]},{"time":2.1667,"value":-8.25,"curve":[2.333,0,2.5,0]},{"time":2.6667}],"translate":[{"curve":"stepped"},{"time":0.6667,"curve":"stepped"},{"time":1.1667,"curve":"stepped"},{"time":2.1667,"curve":"stepped"},{"time":2.6667}],"scale":[{"curve":"stepped"},{"time":0.6667,"curve":"stepped"},{"time":1.1667,"curve":"stepped"},{"time":2.1667,"curve":"stepped"},{"time":2.6667}],"shear":[{"curve":"stepped"},{"time":0.6667,"curve":"stepped"},{"time":1.1667,"curve":"stepped"},{"time":2.1667,"curve":"stepped"},{"time":2.6667}]},"bone12":{"rotate":[{"curve":[0.222,0,0.444,-25.07]},{"time":0.6667,"value":-25.07,"curve":[0.833,-25.07,1,1.3]},{"time":1.1667,"value":1.3,"curve":"stepped"},{"time":2.1667,"value":1.3,"curve":[2.333,1.3,2.5,0]},{"time":2.6667}],"translate":[{"curve":"stepped"},{"time":0.6667,"curve":"stepped"},{"time":1.1667,"curve":"stepped"},{"time":2.1667,"curve":"stepped"},{"time":2.6667}],"scale":[{"curve":"stepped"},{"time":0.6667,"curve":"stepped"},{"time":1.1667,"curve":"stepped"},{"time":2.1667,"curve":"stepped"},{"time":2.6667}],"shear":[{"curve":"stepped"},{"time":0.6667,"curve":"stepped"},{"time":1.1667,"curve":"stepped"},{"time":2.1667,"curve":"stepped"},{"time":2.6667}]},"bone13":{"rotate":[{"curve":"stepped"},{"time":0.6667,"curve":"stepped"},{"time":1.1667,"curve":"stepped"},{"time":2.1667,"curve":"stepped"},{"time":2.6667}],"translate":[{"curve":"stepped"},{"time":0.6667,"curve":"stepped"},{"time":1.1667,"curve":"stepped"},{"time":2.1667,"curve":"stepped"},{"time":2.6667}],"scale":[{"curve":"stepped"},{"time":0.6667,"curve":"stepped"},{"time":1.1667,"curve":"stepped"},{"time":2.1667,"curve":"stepped"},{"time":2.6667}],"shear":[{"curve":"stepped"},{"time":0.6667,"curve":"stepped"},{"time":1.1667,"curve":"stepped"},{"time":2.1667,"curve":"stepped"},{"time":2.6667}]},"bone14":{"rotate":[{"curve":"stepped"},{"time":0.6667,"curve":"stepped"},{"time":1.1667,"curve":"stepped"},{"time":2.1667,"curve":"stepped"},{"time":2.6667}],"translate":[{"curve":"stepped"},{"time":0.6667,"curve":"stepped"},{"time":1.1667,"curve":"stepped"},{"time":2.1667,"curve":"stepped"},{"time":2.6667}],"scale":[{"curve":"stepped"},{"time":0.6667,"curve":"stepped"},{"time":1.1667,"curve":"stepped"},{"time":2.1667,"curve":"stepped"},{"time":2.6667}],"shear":[{"curve":"stepped"},{"time":0.6667,"curve":"stepped"},{"time":1.1667,"curve":"stepped"},{"time":2.1667,"curve":"stepped"},{"time":2.6667}]},"bone15":{"rotate":[{"curve":"stepped"},{"time":0.6667,"curve":"stepped"},{"time":1.1667,"curve":"stepped"},{"time":2.1667,"curve":"stepped"},{"time":2.6667}],"translate":[{"curve":"stepped"},{"time":0.6667,"curve":"stepped"},{"time":1.1667,"curve":"stepped"},{"time":2.1667,"curve":"stepped"},{"time":2.6667}],"scale":[{"curve":"stepped"},{"time":0.6667,"curve":"stepped"},{"time":1.1667,"curve":"stepped"},{"time":2.1667,"curve":"stepped"},{"time":2.6667}],"shear":[{"curve":"stepped"},{"time":0.6667,"curve":"stepped"},{"time":1.1667,"curve":"stepped"},{"time":2.1667,"curve":"stepped"},{"time":2.6667}]},"bone16":{"rotate":[{"curve":"stepped"},{"time":0.6667,"curve":"stepped"},{"time":1.1667,"curve":"stepped"},{"time":2.1667,"curve":"stepped"},{"time":2.6667}],"translate":[{"curve":"stepped"},{"time":0.6667,"curve":"stepped"},{"time":1.1667,"curve":"stepped"},{"time":2.1667,"curve":"stepped"},{"time":2.6667}],"scale":[{"curve":"stepped"},{"time":0.6667,"curve":"stepped"},{"time":1.1667,"curve":"stepped"},{"time":2.1667,"curve":"stepped"},{"time":2.6667}],"shear":[{"curve":"stepped"},{"time":0.6667,"curve":"stepped"},{"time":1.1667,"curve":"stepped"},{"time":2.1667,"curve":"stepped"},{"time":2.6667}]},"bone17":{"rotate":[{"curve":"stepped"},{"time":0.6667,"curve":"stepped"},{"time":1.1667,"curve":"stepped"},{"time":2.1667,"curve":"stepped"},{"time":2.6667}],"translate":[{"curve":"stepped"},{"time":0.6667,"curve":"stepped"},{"time":1.1667,"curve":"stepped"},{"time":2.1667,"curve":"stepped"},{"time":2.6667}],"scale":[{"curve":"stepped"},{"time":0.6667,"curve":"stepped"},{"time":1.1667,"curve":"stepped"},{"time":2.1667,"curve":"stepped"},{"time":2.6667}],"shear":[{"curve":"stepped"},{"time":0.6667,"curve":"stepped"},{"time":1.1667,"curve":"stepped"},{"time":2.1667,"curve":"stepped"},{"time":2.6667}]},"bone18":{"rotate":[{"curve":"stepped"},{"time":0.6667,"curve":"stepped"},{"time":1.1667,"curve":"stepped"},{"time":2.1667,"curve":"stepped"},{"time":2.6667}],"translate":[{"curve":"stepped"},{"time":0.6667,"curve":"stepped"},{"time":1.1667,"curve":"stepped"},{"time":2.1667,"curve":"stepped"},{"time":2.6667}],"scale":[{"curve":"stepped"},{"time":0.6667,"curve":"stepped"},{"time":1.1667,"curve":"stepped"},{"time":2.1667,"curve":"stepped"},{"time":2.6667}],"shear":[{"curve":"stepped"},{"time":0.6667,"curve":"stepped"},{"time":1.1667,"curve":"stepped"},{"time":2.1667,"curve":"stepped"},{"time":2.6667}]},"bone19":{"rotate":[{"curve":"stepped"},{"time":0.6667,"curve":"stepped"},{"time":1.1667,"curve":"stepped"},{"time":2.1667,"curve":"stepped"},{"time":2.6667}],"translate":[{"curve":"stepped"},{"time":0.6667,"curve":"stepped"},{"time":1.1667,"curve":"stepped"},{"time":2.1667,"curve":"stepped"},{"time":2.6667}],"scale":[{"curve":"stepped"},{"time":0.6667,"curve":"stepped"},{"time":1.1667,"curve":"stepped"},{"time":2.1667,"curve":"stepped"},{"time":2.6667}],"shear":[{"curve":"stepped"},{"time":0.6667,"curve":"stepped"},{"time":1.1667,"curve":"stepped"},{"time":2.1667,"curve":"stepped"},{"time":2.6667}]},"bone20":{"rotate":[{"curve":"stepped"},{"time":0.6667,"curve":"stepped"},{"time":1.1667,"curve":"stepped"},{"time":2.1667,"curve":"stepped"},{"time":2.6667}],"translate":[{"curve":"stepped"},{"time":0.6667,"curve":"stepped"},{"time":1.1667,"curve":"stepped"},{"time":2.1667,"curve":"stepped"},{"time":2.6667}],"scale":[{"curve":"stepped"},{"time":0.6667,"curve":"stepped"},{"time":1.1667,"curve":"stepped"},{"time":2.1667,"curve":"stepped"},{"time":2.6667}],"shear":[{"curve":"stepped"},{"time":0.6667,"curve":"stepped"},{"time":1.1667,"curve":"stepped"},{"time":2.1667,"curve":"stepped"},{"time":2.6667}]},"bone21":{"rotate":[{"curve":"stepped"},{"time":0.6667,"curve":"stepped"},{"time":1.1667,"curve":"stepped"},{"time":2.1667,"curve":"stepped"},{"time":2.6667}],"translate":[{"curve":"stepped"},{"time":0.6667,"curve":"stepped"},{"time":1.1667,"curve":"stepped"},{"time":2.1667,"curve":"stepped"},{"time":2.6667}],"scale":[{"curve":"stepped"},{"time":0.6667,"curve":"stepped"},{"time":1.1667,"curve":"stepped"},{"time":2.1667,"curve":"stepped"},{"time":2.6667}],"shear":[{"curve":"stepped"},{"time":0.6667,"curve":"stepped"},{"time":1.1667,"curve":"stepped"},{"time":2.1667,"curve":"stepped"},{"time":2.6667}]},"bone22":{"rotate":[{"curve":"stepped"},{"time":0.6667,"curve":"stepped"},{"time":1.1667,"curve":"stepped"},{"time":2.1667,"curve":"stepped"},{"time":2.6667}],"translate":[{"curve":"stepped"},{"time":0.6667,"curve":"stepped"},{"time":1.1667,"curve":"stepped"},{"time":2.1667,"curve":"stepped"},{"time":2.6667}],"scale":[{"curve":"stepped"},{"time":0.6667,"curve":"stepped"},{"time":1.1667,"curve":"stepped"},{"time":2.1667,"curve":"stepped"},{"time":2.6667}],"shear":[{"curve":"stepped"},{"time":0.6667,"curve":"stepped"},{"time":1.1667,"curve":"stepped"},{"time":2.1667,"curve":"stepped"},{"time":2.6667}]},"bone23":{"rotate":[{"value":-0.7,"curve":[0.222,-0.7,0.444,-0.7]},{"time":0.6667,"value":-0.7,"curve":[0.833,-0.7,1,-0.7]},{"time":1.1667,"value":-0.7,"curve":"stepped"},{"time":2.1667,"value":-0.7,"curve":[2.333,-0.7,2.5,-0.7]},{"time":2.6667,"value":-0.7}],"translate":[{"curve":"stepped"},{"time":0.6667,"curve":"stepped"},{"time":1.1667,"curve":"stepped"},{"time":2.1667,"curve":"stepped"},{"time":2.6667}],"scale":[{"curve":"stepped"},{"time":0.6667,"curve":"stepped"},{"time":1.1667,"curve":"stepped"},{"time":2.1667,"curve":"stepped"},{"time":2.6667}],"shear":[{"curve":"stepped"},{"time":0.6667,"curve":"stepped"},{"time":1.1667,"curve":"stepped"},{"time":2.1667,"curve":"stepped"},{"time":2.6667}]},"bone24":{"rotate":[{"value":1.71,"curve":[0.222,1.71,0.444,1.71]},{"time":0.6667,"value":1.71,"curve":[0.833,1.71,1,1.71]},{"time":1.1667,"value":1.71,"curve":"stepped"},{"time":2.1667,"value":1.71,"curve":[2.333,1.71,2.5,1.71]},{"time":2.6667,"value":1.71}],"translate":[{"curve":"stepped"},{"time":0.6667,"curve":"stepped"},{"time":1.1667,"curve":"stepped"},{"time":2.1667,"curve":"stepped"},{"time":2.6667}],"scale":[{"curve":"stepped"},{"time":0.6667,"curve":"stepped"},{"time":1.1667,"curve":"stepped"},{"time":2.1667,"curve":"stepped"},{"time":2.6667}],"shear":[{"curve":"stepped"},{"time":0.6667,"curve":"stepped"},{"time":1.1667,"curve":"stepped"},{"time":2.1667,"curve":"stepped"},{"time":2.6667}]},"ikr":{"rotate":[{"curve":"stepped"},{"time":0.6667,"curve":"stepped"},{"time":1.1667,"curve":"stepped"},{"time":2.1667,"curve":"stepped"},{"time":2.6667}],"translate":[{"curve":"stepped"},{"time":0.6667,"curve":"stepped"},{"time":1.1667,"curve":"stepped"},{"time":2.1667,"curve":"stepped"},{"time":2.6667}],"scale":[{"curve":"stepped"},{"time":0.6667,"curve":"stepped"},{"time":1.1667,"curve":"stepped"},{"time":2.1667,"curve":"stepped"},{"time":2.6667}],"shear":[{"curve":"stepped"},{"time":0.6667,"curve":"stepped"},{"time":1.1667,"curve":"stepped"},{"time":2.1667,"curve":"stepped"},{"time":2.6667}]},"ikl":{"rotate":[{"curve":"stepped"},{"time":0.6667,"curve":"stepped"},{"time":1.1667,"curve":"stepped"},{"time":2.1667,"curve":"stepped"},{"time":2.6667}],"translate":[{"curve":"stepped"},{"time":0.6667,"curve":"stepped"},{"time":1.1667,"curve":"stepped"},{"time":2.1667,"curve":"stepped"},{"time":2.6667}],"scale":[{"curve":"stepped"},{"time":0.6667,"curve":"stepped"},{"time":1.1667,"curve":"stepped"},{"time":2.1667,"curve":"stepped"},{"time":2.6667}],"shear":[{"curve":"stepped"},{"time":0.6667,"curve":"stepped"},{"time":1.1667,"curve":"stepped"},{"time":2.1667,"curve":"stepped"},{"time":2.6667}]}}},"idle":{"bones":{"root":{"rotate":[{"curve":"stepped"},{"time":0.5,"curve":"stepped"},{"time":1,"curve":"stepped"},{"time":1.5,"curve":"stepped"},{"time":2}],"translate":[{"curve":"stepped"},{"time":0.5,"curve":"stepped"},{"time":1,"curve":"stepped"},{"time":1.5,"curve":"stepped"},{"time":2}],"scale":[{"curve":"stepped"},{"time":0.5,"curve":"stepped"},{"time":1,"curve":"stepped"},{"time":1.5,"curve":"stepped"},{"time":2}],"shear":[{"curve":"stepped"},{"time":0.5,"curve":"stepped"},{"time":1,"curve":"stepped"},{"time":1.5,"curve":"stepped"},{"time":2}]},"bone":{"rotate":[{"curve":"stepped"},{"time":0.5,"curve":"stepped"},{"time":1,"curve":"stepped"},{"time":1.5,"curve":"stepped"},{"time":2}],"translate":[{"curve":"stepped"},{"time":0.5,"curve":"stepped"},{"time":1,"curve":"stepped"},{"time":1.5,"curve":"stepped"},{"time":2}],"scale":[{"curve":"stepped"},{"time":0.5,"curve":"stepped"},{"time":1,"curve":"stepped"},{"time":1.5,"curve":"stepped"},{"time":2}],"shear":[{"curve":"stepped"},{"time":0.5,"curve":"stepped"},{"time":1,"curve":"stepped"},{"time":1.5,"curve":"stepped"},{"time":2}]},"bone2":{"rotate":[{"curve":"stepped"},{"time":0.5,"curve":"stepped"},{"time":1,"curve":"stepped"},{"time":1.5,"curve":"stepped"},{"time":2}],"translate":[{"curve":"stepped"},{"time":0.5,"curve":"stepped"},{"time":1,"curve":"stepped"},{"time":1.5,"curve":"stepped"},{"time":2}],"scale":[{"curve":"stepped"},{"time":0.5,"curve":"stepped"},{"time":1,"curve":"stepped"},{"time":1.5,"curve":"stepped"},{"time":2}],"shear":[{"curve":"stepped"},{"time":0.5,"curve":"stepped"},{"time":1,"curve":"stepped"},{"time":1.5,"curve":"stepped"},{"time":2}]},"bone3":{"rotate":[{"curve":"stepped"},{"time":0.5,"curve":"stepped"},{"time":1,"curve":"stepped"},{"time":1.5,"curve":"stepped"},{"time":2}],"translate":[{"curve":[0.167,0,0.333,-14.99,0.167,0,0.333,-0.14]},{"time":0.5,"x":-14.99,"y":-0.14,"curve":[0.667,-14.99,0.833,0,0.667,-0.14,0.833,0]},{"time":1,"curve":[1.167,0,1.333,-14.99,1.167,0,1.333,-0.14]},{"time":1.5,"x":-14.99,"y":-0.14,"curve":[1.667,-14.99,1.833,0,1.667,-0.14,1.833,0]},{"time":2}],"scale":[{"curve":"stepped"},{"time":0.5,"curve":"stepped"},{"time":1,"curve":"stepped"},{"time":1.5,"curve":"stepped"},{"time":2}],"shear":[{"curve":"stepped"},{"time":0.5,"curve":"stepped"},{"time":1,"curve":"stepped"},{"time":1.5,"curve":"stepped"},{"time":2}]},"bone4":{"rotate":[{"curve":"stepped"},{"time":0.5,"curve":"stepped"},{"time":1,"curve":"stepped"},{"time":1.5,"curve":"stepped"},{"time":2}],"translate":[{"curve":"stepped"},{"time":0.5,"curve":"stepped"},{"time":1,"curve":"stepped"},{"time":1.5,"curve":"stepped"},{"time":2}],"scale":[{"curve":"stepped"},{"time":0.5,"curve":"stepped"},{"time":1,"curve":"stepped"},{"time":1.5,"curve":"stepped"},{"time":2}],"shear":[{"curve":"stepped"},{"time":0.5,"curve":"stepped"},{"time":1,"curve":"stepped"},{"time":1.5,"curve":"stepped"},{"time":2}]},"bone5":{"rotate":[{"curve":"stepped"},{"time":0.5,"curve":"stepped"},{"time":1,"curve":"stepped"},{"time":1.5,"curve":"stepped"},{"time":2}],"translate":[{"curve":"stepped"},{"time":0.5,"curve":"stepped"},{"time":1,"curve":"stepped"},{"time":1.5,"curve":"stepped"},{"time":2}],"scale":[{"curve":"stepped"},{"time":0.5,"curve":"stepped"},{"time":1,"curve":"stepped"},{"time":1.5,"curve":"stepped"},{"time":2}],"shear":[{"curve":"stepped"},{"time":0.5,"curve":"stepped"},{"time":1,"curve":"stepped"},{"time":1.5,"curve":"stepped"},{"time":2}]},"bone6":{"rotate":[{"curve":[0.167,0,0.333,-5.95]},{"time":0.5,"value":-5.95,"curve":[0.667,-5.95,0.833,0]},{"time":1,"curve":[1.167,0,1.333,-5.95]},{"time":1.5,"value":-5.95,"curve":[1.667,-5.95,1.833,0]},{"time":2}],"translate":[{"curve":"stepped"},{"time":0.5,"curve":"stepped"},{"time":1,"curve":"stepped"},{"time":1.5,"curve":"stepped"},{"time":2}],"scale":[{"curve":"stepped"},{"time":0.5,"curve":"stepped"},{"time":1,"curve":"stepped"},{"time":1.5,"curve":"stepped"},{"time":2}],"shear":[{"curve":"stepped"},{"time":0.5,"curve":"stepped"},{"time":1,"curve":"stepped"},{"time":1.5,"curve":"stepped"},{"time":2}]},"bone7":{"rotate":[{"curve":"stepped"},{"time":0.5,"curve":"stepped"},{"time":1,"curve":"stepped"},{"time":1.5,"curve":"stepped"},{"time":2}],"translate":[{"curve":"stepped"},{"time":0.5,"curve":"stepped"},{"time":1,"curve":"stepped"},{"time":1.5,"curve":"stepped"},{"time":2}],"scale":[{"curve":"stepped"},{"time":0.5,"curve":"stepped"},{"time":1,"curve":"stepped"},{"time":1.4333,"curve":[1.456,1,1.478,0.117,1.456,1,1.478,1]},{"time":1.5,"x":0.117,"curve":[1.522,0.117,1.544,1,1.522,1,1.544,1]},{"time":1.5667,"curve":"stepped"},{"time":2}],"shear":[{"curve":"stepped"},{"time":0.5,"curve":"stepped"},{"time":1,"curve":"stepped"},{"time":1.5,"curve":"stepped"},{"time":2}]},"bone8":{"rotate":[{"curve":"stepped"},{"time":0.5,"curve":"stepped"},{"time":1,"curve":"stepped"},{"time":1.5,"curve":"stepped"},{"time":2}],"translate":[{"curve":"stepped"},{"time":0.5,"curve":"stepped"},{"time":1,"curve":"stepped"},{"time":1.5,"curve":"stepped"},{"time":2}],"scale":[{"curve":"stepped"},{"time":0.5,"curve":"stepped"},{"time":1,"curve":"stepped"},{"time":1.4333,"curve":[1.456,1,1.478,0.117,1.456,1,1.478,1]},{"time":1.5,"x":0.117,"curve":[1.522,0.117,1.544,1,1.522,1,1.544,1]},{"time":1.5667,"curve":"stepped"},{"time":2}],"shear":[{"curve":"stepped"},{"time":0.5,"curve":"stepped"},{"time":1,"curve":"stepped"},{"time":1.5,"curve":"stepped"},{"time":2}]},"bone9":{"rotate":[{"curve":"stepped"},{"time":0.5,"curve":"stepped"},{"time":1,"curve":"stepped"},{"time":1.5,"curve":"stepped"},{"time":2}],"translate":[{"curve":"stepped"},{"time":0.5,"curve":"stepped"},{"time":1,"curve":"stepped"},{"time":1.5,"curve":"stepped"},{"time":2}],"scale":[{"curve":"stepped"},{"time":0.5,"curve":"stepped"},{"time":1,"curve":"stepped"},{"time":1.5,"curve":"stepped"},{"time":2}],"shear":[{"curve":"stepped"},{"time":0.5,"curve":"stepped"},{"time":1,"curve":"stepped"},{"time":1.5,"curve":"stepped"},{"time":2}]},"bone10":{"rotate":[{"curve":[0.167,0,0.333,-1.1]},{"time":0.5,"value":-1.1,"curve":[0.667,-1.1,0.833,0]},{"time":1,"curve":[1.167,0,1.333,-1.1]},{"time":1.5,"value":-1.1,"curve":[1.667,-1.1,1.833,0]},{"time":2}],"translate":[{"curve":[0.167,0,0.333,1.2,0.167,0,0.333,-0.33]},{"time":0.5,"x":1.2,"y":-0.33,"curve":[0.667,1.2,0.833,0,0.667,-0.33,0.833,0]},{"time":1,"curve":[1.167,0,1.333,1.2,1.167,0,1.333,-0.33]},{"time":1.5,"x":1.2,"y":-0.33,"curve":[1.667,1.2,1.833,0,1.667,-0.33,1.833,0]},{"time":2}],"scale":[{"curve":"stepped"},{"time":0.5,"curve":"stepped"},{"time":1,"curve":"stepped"},{"time":1.5,"curve":"stepped"},{"time":2}],"shear":[{"curve":"stepped"},{"time":0.5,"curve":"stepped"},{"time":1,"curve":"stepped"},{"time":1.5,"curve":"stepped"},{"time":2}]},"bone11":{"rotate":[{"curve":"stepped"},{"time":0.5,"curve":"stepped"},{"time":1,"curve":"stepped"},{"time":1.5,"curve":"stepped"},{"time":2}],"translate":[{"curve":"stepped"},{"time":0.5,"curve":"stepped"},{"time":1,"curve":"stepped"},{"time":1.5,"curve":"stepped"},{"time":2}],"scale":[{"curve":"stepped"},{"time":0.5,"curve":"stepped"},{"time":1,"curve":"stepped"},{"time":1.5,"curve":"stepped"},{"time":2}],"shear":[{"curve":"stepped"},{"time":0.5,"curve":"stepped"},{"time":1,"curve":"stepped"},{"time":1.5,"curve":"stepped"},{"time":2}]},"bone12":{"rotate":[{"curve":"stepped"},{"time":0.5,"curve":"stepped"},{"time":1,"curve":"stepped"},{"time":1.5,"curve":"stepped"},{"time":2}],"translate":[{"curve":"stepped"},{"time":0.5,"curve":"stepped"},{"time":1,"curve":"stepped"},{"time":1.5,"curve":"stepped"},{"time":2}],"scale":[{"curve":"stepped"},{"time":0.5,"curve":"stepped"},{"time":1,"curve":"stepped"},{"time":1.5,"curve":"stepped"},{"time":2}],"shear":[{"curve":"stepped"},{"time":0.5,"curve":"stepped"},{"time":1,"curve":"stepped"},{"time":1.5,"curve":"stepped"},{"time":2}]},"bone13":{"rotate":[{"curve":"stepped"},{"time":0.5,"curve":"stepped"},{"time":1,"curve":"stepped"},{"time":1.5,"curve":"stepped"},{"time":2}],"translate":[{"curve":"stepped"},{"time":0.5,"curve":"stepped"},{"time":1,"curve":"stepped"},{"time":1.5,"curve":"stepped"},{"time":2}],"scale":[{"curve":"stepped"},{"time":0.5,"curve":"stepped"},{"time":1,"curve":"stepped"},{"time":1.5,"curve":"stepped"},{"time":2}],"shear":[{"curve":"stepped"},{"time":0.5,"curve":"stepped"},{"time":1,"curve":"stepped"},{"time":1.5,"curve":"stepped"},{"time":2}]},"bone14":{"rotate":[{"curve":[0.167,0,0.333,2.31]},{"time":0.5,"value":2.31,"curve":[0.667,2.31,0.833,0]},{"time":1,"curve":[1.167,0,1.333,2.31]},{"time":1.5,"value":2.31,"curve":[1.667,2.31,1.833,0]},{"time":2}],"translate":[{"curve":[0.167,0,0.333,0.93,0.167,0,0.333,-4.6]},{"time":0.5,"x":0.93,"y":-4.6,"curve":[0.667,0.93,0.833,0,0.667,-4.6,0.833,0]},{"time":1,"curve":[1.167,0,1.333,0.93,1.167,0,1.333,-4.6]},{"time":1.5,"x":0.93,"y":-4.6,"curve":[1.667,0.93,1.833,0,1.667,-4.6,1.833,0]},{"time":2}],"scale":[{"curve":"stepped"},{"time":0.5,"curve":"stepped"},{"time":1,"curve":"stepped"},{"time":1.5,"curve":"stepped"},{"time":2}],"shear":[{"curve":"stepped"},{"time":0.5,"curve":"stepped"},{"time":1,"curve":"stepped"},{"time":1.5,"curve":"stepped"},{"time":2}]},"bone15":{"rotate":[{"curve":"stepped"},{"time":0.5,"curve":"stepped"},{"time":1,"curve":"stepped"},{"time":1.5,"curve":"stepped"},{"time":2}],"translate":[{"curve":"stepped"},{"time":0.5,"curve":"stepped"},{"time":1,"curve":"stepped"},{"time":1.5,"curve":"stepped"},{"time":2}],"scale":[{"curve":"stepped"},{"time":0.5,"curve":"stepped"},{"time":1,"curve":"stepped"},{"time":1.5,"curve":"stepped"},{"time":2}],"shear":[{"curve":"stepped"},{"time":0.5,"curve":"stepped"},{"time":1,"curve":"stepped"},{"time":1.5,"curve":"stepped"},{"time":2}]},"bone16":{"rotate":[{"curve":"stepped"},{"time":0.5,"curve":"stepped"},{"time":1,"curve":"stepped"},{"time":1.5,"curve":"stepped"},{"time":2}],"translate":[{"curve":"stepped"},{"time":0.5,"curve":"stepped"},{"time":1,"curve":"stepped"},{"time":1.5,"curve":"stepped"},{"time":2}],"scale":[{"curve":"stepped"},{"time":0.5,"curve":"stepped"},{"time":1,"curve":"stepped"},{"time":1.5,"curve":"stepped"},{"time":2}],"shear":[{"curve":"stepped"},{"time":0.5,"curve":"stepped"},{"time":1,"curve":"stepped"},{"time":1.5,"curve":"stepped"},{"time":2}]},"bone17":{"rotate":[{"curve":"stepped"},{"time":0.5,"curve":"stepped"},{"time":1,"curve":"stepped"},{"time":1.5,"curve":"stepped"},{"time":2}],"translate":[{"curve":"stepped"},{"time":0.5,"curve":"stepped"},{"time":1,"curve":"stepped"},{"time":1.5,"curve":"stepped"},{"time":2}],"scale":[{"curve":"stepped"},{"time":0.5,"curve":"stepped"},{"time":1,"curve":"stepped"},{"time":1.5,"curve":"stepped"},{"time":2}],"shear":[{"curve":"stepped"},{"time":0.5,"curve":"stepped"},{"time":1,"curve":"stepped"},{"time":1.5,"curve":"stepped"},{"time":2}]},"bone18":{"rotate":[{"curve":"stepped"},{"time":0.5,"curve":"stepped"},{"time":1,"curve":"stepped"},{"time":1.5,"curve":"stepped"},{"time":2}],"translate":[{"curve":[0.167,0,0.333,-10.11,0.167,0,0.333,9.34]},{"time":0.5,"x":-10.11,"y":9.34,"curve":[0.667,-10.11,0.833,0,0.667,9.34,0.833,0]},{"time":1,"curve":[1.167,0,1.333,-10.11,1.167,0,1.333,9.34]},{"time":1.5,"x":-10.11,"y":9.34,"curve":[1.667,-10.11,1.833,0,1.667,9.34,1.833,0]},{"time":2}],"scale":[{"curve":"stepped"},{"time":0.5,"curve":"stepped"},{"time":1,"curve":"stepped"},{"time":1.5,"curve":"stepped"},{"time":2}],"shear":[{"curve":"stepped"},{"time":0.5,"curve":"stepped"},{"time":1,"curve":"stepped"},{"time":1.5,"curve":"stepped"},{"time":2}]},"bone19":{"rotate":[{"curve":"stepped"},{"time":0.5,"curve":"stepped"},{"time":1,"curve":"stepped"},{"time":1.5,"curve":"stepped"},{"time":2}],"translate":[{"curve":"stepped"},{"time":0.5,"curve":"stepped"},{"time":1,"curve":"stepped"},{"time":1.5,"curve":"stepped"},{"time":2}],"scale":[{"curve":"stepped"},{"time":0.5,"curve":"stepped"},{"time":1,"curve":"stepped"},{"time":1.5,"curve":"stepped"},{"time":2}],"shear":[{"curve":"stepped"},{"time":0.5,"curve":"stepped"},{"time":1,"curve":"stepped"},{"time":1.5,"curve":"stepped"},{"time":2}]},"bone20":{"rotate":[{"curve":"stepped"},{"time":0.5,"curve":"stepped"},{"time":1,"curve":"stepped"},{"time":1.5,"curve":"stepped"},{"time":2}],"translate":[{"curve":[0.167,0,0.333,-20.33,0.167,0,0.333,-4.47]},{"time":0.5,"x":-20.33,"y":-4.47,"curve":[0.667,-20.33,0.833,0,0.667,-4.47,0.833,0]},{"time":1,"curve":[1.167,0,1.333,-20.33,1.167,0,1.333,-4.47]},{"time":1.5,"x":-20.33,"y":-4.47,"curve":[1.667,-20.33,1.833,0,1.667,-4.47,1.833,0]},{"time":2}],"scale":[{"curve":"stepped"},{"time":0.5,"curve":"stepped"},{"time":1,"curve":"stepped"},{"time":1.5,"curve":"stepped"},{"time":2}],"shear":[{"curve":"stepped"},{"time":0.5,"curve":"stepped"},{"time":1,"curve":"stepped"},{"time":1.5,"curve":"stepped"},{"time":2}]},"bone21":{"rotate":[{"curve":"stepped"},{"time":0.5,"curve":"stepped"},{"time":1,"curve":"stepped"},{"time":1.5,"curve":"stepped"},{"time":2}],"translate":[{"curve":"stepped"},{"time":0.5,"curve":"stepped"},{"time":1,"curve":"stepped"},{"time":1.5,"curve":"stepped"},{"time":2}],"scale":[{"curve":"stepped"},{"time":0.5,"curve":"stepped"},{"time":1,"curve":"stepped"},{"time":1.5,"curve":"stepped"},{"time":2}],"shear":[{"curve":"stepped"},{"time":0.5,"curve":"stepped"},{"time":1,"curve":"stepped"},{"time":1.5,"curve":"stepped"},{"time":2}]},"bone22":{"rotate":[{"curve":"stepped"},{"time":0.5,"curve":"stepped"},{"time":1,"curve":"stepped"},{"time":1.5,"curve":"stepped"},{"time":2}],"translate":[{"curve":"stepped"},{"time":0.5,"curve":"stepped"},{"time":1,"curve":"stepped"},{"time":1.5,"curve":"stepped"},{"time":2}],"scale":[{"curve":"stepped"},{"time":0.5,"curve":"stepped"},{"time":1,"curve":"stepped"},{"time":1.5,"curve":"stepped"},{"time":2}],"shear":[{"curve":"stepped"},{"time":0.5,"curve":"stepped"},{"time":1,"curve":"stepped"},{"time":1.5,"curve":"stepped"},{"time":2}]},"bone23":{"rotate":[{"value":-0.7,"curve":"stepped"},{"time":0.5,"value":-0.7,"curve":"stepped"},{"time":1,"value":-0.7,"curve":"stepped"},{"time":1.5,"value":-0.7,"curve":"stepped"},{"time":2,"value":-0.7}],"translate":[{"curve":"stepped"},{"time":0.5,"curve":"stepped"},{"time":1,"curve":"stepped"},{"time":1.5,"curve":"stepped"},{"time":2}],"scale":[{"curve":"stepped"},{"time":0.5,"curve":"stepped"},{"time":1,"curve":"stepped"},{"time":1.5,"curve":"stepped"},{"time":2}],"shear":[{"curve":"stepped"},{"time":0.5,"curve":"stepped"},{"time":1,"curve":"stepped"},{"time":1.5,"curve":"stepped"},{"time":2}]},"bone24":{"rotate":[{"value":1.71,"curve":"stepped"},{"time":0.5,"value":1.71,"curve":"stepped"},{"time":1,"value":1.71,"curve":"stepped"},{"time":1.5,"value":1.71,"curve":"stepped"},{"time":2,"value":1.71}],"translate":[{"curve":"stepped"},{"time":0.5,"curve":"stepped"},{"time":1,"curve":"stepped"},{"time":1.5,"curve":"stepped"},{"time":2}],"scale":[{"curve":"stepped"},{"time":0.5,"curve":"stepped"},{"time":1,"curve":"stepped"},{"time":1.5,"curve":"stepped"},{"time":2}],"shear":[{"curve":"stepped"},{"time":0.5,"curve":"stepped"},{"time":1,"curve":"stepped"},{"time":1.5,"curve":"stepped"},{"time":2}]},"ikr":{"rotate":[{"curve":"stepped"},{"time":0.5,"curve":"stepped"},{"time":1,"curve":"stepped"},{"time":1.5,"curve":"stepped"},{"time":2}],"translate":[{"curve":"stepped"},{"time":0.5,"curve":"stepped"},{"time":1,"curve":"stepped"},{"time":1.5,"curve":"stepped"},{"time":2}],"scale":[{"curve":"stepped"},{"time":0.5,"curve":"stepped"},{"time":1,"curve":"stepped"},{"time":1.5,"curve":"stepped"},{"time":2}],"shear":[{"curve":"stepped"},{"time":0.5,"curve":"stepped"},{"time":1,"curve":"stepped"},{"time":1.5,"curve":"stepped"},{"time":2}]},"ikl":{"rotate":[{"curve":"stepped"},{"time":0.5,"curve":"stepped"},{"time":1,"curve":"stepped"},{"time":1.5,"curve":"stepped"},{"time":2}],"translate":[{"curve":"stepped"},{"time":0.5,"curve":"stepped"},{"time":1,"curve":"stepped"},{"time":1.5,"curve":"stepped"},{"time":2}],"scale":[{"curve":"stepped"},{"time":0.5,"curve":"stepped"},{"time":1,"curve":"stepped"},{"time":1.5,"curve":"stepped"},{"time":2}],"shear":[{"curve":"stepped"},{"time":0.5,"curve":"stepped"},{"time":1,"curve":"stepped"},{"time":1.5,"curve":"stepped"},{"time":2}]}}},"look_player_down":{"bones":{"root":{"rotate":[{"curve":"stepped"},{"time":1,"curve":"stepped"},{"time":2}],"translate":[{"curve":"stepped"},{"time":1,"curve":"stepped"},{"time":2}],"scale":[{"curve":"stepped"},{"time":1,"curve":"stepped"},{"time":2}],"shear":[{"curve":"stepped"},{"time":1,"curve":"stepped"},{"time":2}]},"bone":{"rotate":[{"curve":"stepped"},{"time":1,"curve":"stepped"},{"time":2}],"translate":[{"curve":"stepped"},{"time":1,"curve":"stepped"},{"time":2}],"scale":[{"curve":"stepped"},{"time":1,"curve":"stepped"},{"time":2}],"shear":[{"curve":"stepped"},{"time":1,"curve":"stepped"},{"time":2}]},"bone2":{"rotate":[{"curve":"stepped"},{"time":1,"curve":"stepped"},{"time":2}],"translate":[{"curve":"stepped"},{"time":1,"curve":"stepped"},{"time":2}],"scale":[{"curve":"stepped"},{"time":1,"curve":"stepped"},{"time":2}],"shear":[{"curve":"stepped"},{"time":1,"curve":"stepped"},{"time":2}]},"bone3":{"rotate":[{"curve":"stepped"},{"time":1,"curve":"stepped"},{"time":2}],"translate":[{"curve":"stepped"},{"time":1,"curve":"stepped"},{"time":2}],"scale":[{"curve":"stepped"},{"time":1,"curve":"stepped"},{"time":2}],"shear":[{"curve":"stepped"},{"time":1,"curve":"stepped"},{"time":2}]},"bone4":{"rotate":[{"curve":"stepped"},{"time":1,"curve":"stepped"},{"time":2}],"translate":[{"curve":"stepped"},{"time":1,"curve":"stepped"},{"time":2}],"scale":[{"curve":"stepped"},{"time":1,"curve":"stepped"},{"time":2}],"shear":[{"curve":"stepped"},{"time":1,"curve":"stepped"},{"time":2}]},"bone5":{"rotate":[{"value":22.11,"curve":"stepped"},{"time":1,"value":22.11,"curve":"stepped"},{"time":2,"value":22.11}],"translate":[{"curve":"stepped"},{"time":1,"curve":"stepped"},{"time":2}],"scale":[{"curve":"stepped"},{"time":1,"curve":"stepped"},{"time":2}],"shear":[{"curve":"stepped"},{"time":1,"curve":"stepped"},{"time":2}]},"bone6":{"rotate":[{"value":0.66,"curve":"stepped"},{"time":1,"value":0.66,"curve":"stepped"},{"time":2,"value":0.66}],"translate":[{"curve":"stepped"},{"time":1,"curve":"stepped"},{"time":2}],"scale":[{"curve":"stepped"},{"time":1,"curve":"stepped"},{"time":2}],"shear":[{"curve":"stepped"},{"time":1,"curve":"stepped"},{"time":2}]},"bone7":{"rotate":[{"curve":"stepped"},{"time":1,"curve":"stepped"},{"time":2}],"translate":[{"curve":"stepped"},{"time":1,"curve":"stepped"},{"time":2}],"scale":[{"curve":"stepped"},{"time":1,"curve":"stepped"},{"time":1.5,"curve":[1.511,1,1.539,0.288,1.511,1,1.539,1]},{"time":1.5667,"x":0.288,"curve":[1.595,0.288,1.622,1,1.595,1,1.622,1]},{"time":1.6333,"curve":"stepped"},{"time":2}],"shear":[{"curve":"stepped"},{"time":1,"curve":"stepped"},{"time":2}]},"bone8":{"rotate":[{"curve":"stepped"},{"time":1,"curve":"stepped"},{"time":2}],"translate":[{"curve":"stepped"},{"time":1,"curve":"stepped"},{"time":2}],"scale":[{"curve":"stepped"},{"time":1,"curve":"stepped"},{"time":1.5,"curve":[1.511,1,1.539,0.288,1.511,1,1.539,1]},{"time":1.5667,"x":0.288,"curve":[1.595,0.288,1.622,1,1.595,1,1.622,1]},{"time":1.6333,"curve":"stepped"},{"time":2}],"shear":[{"curve":"stepped"},{"time":1,"curve":"stepped"},{"time":2}]},"bone9":{"rotate":[{"curve":"stepped"},{"time":1,"curve":"stepped"},{"time":2}],"translate":[{"curve":"stepped"},{"time":1,"curve":"stepped"},{"time":2}],"scale":[{"curve":"stepped"},{"time":1,"curve":"stepped"},{"time":2}],"shear":[{"curve":"stepped"},{"time":1,"curve":"stepped"},{"time":2}]},"bone10":{"rotate":[{"curve":"stepped"},{"time":1,"curve":"stepped"},{"time":2}],"translate":[{"curve":"stepped"},{"time":1,"curve":"stepped"},{"time":2}],"scale":[{"curve":"stepped"},{"time":1,"curve":"stepped"},{"time":2}],"shear":[{"curve":"stepped"},{"time":1,"curve":"stepped"},{"time":2}]},"bone11":{"rotate":[{"curve":"stepped"},{"time":1,"curve":"stepped"},{"time":2}],"translate":[{"curve":"stepped"},{"time":1,"curve":"stepped"},{"time":2}],"scale":[{"curve":"stepped"},{"time":1,"curve":"stepped"},{"time":2}],"shear":[{"curve":"stepped"},{"time":1,"curve":"stepped"},{"time":2}]},"bone12":{"rotate":[{"curve":"stepped"},{"time":1,"curve":"stepped"},{"time":2}],"translate":[{"curve":"stepped"},{"time":1,"curve":"stepped"},{"time":2}],"scale":[{"curve":"stepped"},{"time":1,"curve":"stepped"},{"time":2}],"shear":[{"curve":"stepped"},{"time":1,"curve":"stepped"},{"time":2}]},"bone13":{"rotate":[{"curve":"stepped"},{"time":1,"curve":"stepped"},{"time":2}],"translate":[{"curve":"stepped"},{"time":1,"curve":"stepped"},{"time":2}],"scale":[{"curve":"stepped"},{"time":1,"curve":"stepped"},{"time":2}],"shear":[{"curve":"stepped"},{"time":1,"curve":"stepped"},{"time":2}]},"bone14":{"rotate":[{"curve":"stepped"},{"time":1,"curve":"stepped"},{"time":2}],"translate":[{"curve":"stepped"},{"time":1,"curve":"stepped"},{"time":2}],"scale":[{"curve":"stepped"},{"time":1,"curve":"stepped"},{"time":2}],"shear":[{"curve":"stepped"},{"time":1,"curve":"stepped"},{"time":2}]},"bone15":{"rotate":[{"curve":"stepped"},{"time":1,"curve":"stepped"},{"time":2}],"translate":[{"curve":"stepped"},{"time":1,"curve":"stepped"},{"time":2}],"scale":[{"curve":"stepped"},{"time":1,"curve":"stepped"},{"time":2}],"shear":[{"curve":"stepped"},{"time":1,"curve":"stepped"},{"time":2}]},"bone16":{"rotate":[{"curve":"stepped"},{"time":1,"curve":"stepped"},{"time":2}],"translate":[{"curve":"stepped"},{"time":1,"curve":"stepped"},{"time":2}],"scale":[{"curve":"stepped"},{"time":1,"curve":"stepped"},{"time":2}],"shear":[{"curve":"stepped"},{"time":1,"curve":"stepped"},{"time":2}]},"bone17":{"rotate":[{"curve":"stepped"},{"time":1,"curve":"stepped"},{"time":2}],"translate":[{"curve":"stepped"},{"time":1,"curve":"stepped"},{"time":2}],"scale":[{"curve":"stepped"},{"time":1,"curve":"stepped"},{"time":2}],"shear":[{"curve":"stepped"},{"time":1,"curve":"stepped"},{"time":2}]},"bone18":{"rotate":[{"curve":"stepped"},{"time":1,"curve":"stepped"},{"time":2}],"translate":[{"curve":"stepped"},{"time":1,"curve":"stepped"},{"time":2}],"scale":[{"curve":"stepped"},{"time":1,"curve":"stepped"},{"time":2}],"shear":[{"curve":"stepped"},{"time":1,"curve":"stepped"},{"time":2}]},"bone19":{"rotate":[{"curve":"stepped"},{"time":1,"curve":"stepped"},{"time":2}],"translate":[{"curve":"stepped"},{"time":1,"curve":"stepped"},{"time":2}],"scale":[{"curve":"stepped"},{"time":1,"curve":"stepped"},{"time":2}],"shear":[{"curve":"stepped"},{"time":1,"curve":"stepped"},{"time":2}]},"bone20":{"rotate":[{"curve":"stepped"},{"time":1,"curve":"stepped"},{"time":2}],"translate":[{"curve":"stepped"},{"time":1,"curve":"stepped"},{"time":2}],"scale":[{"curve":"stepped"},{"time":1,"curve":"stepped"},{"time":2}],"shear":[{"curve":"stepped"},{"time":1,"curve":"stepped"},{"time":2}]},"bone21":{"rotate":[{"curve":"stepped"},{"time":1,"curve":"stepped"},{"time":2}],"translate":[{"curve":"stepped"},{"time":1,"curve":"stepped"},{"time":2}],"scale":[{"curve":"stepped"},{"time":1,"curve":"stepped"},{"time":2}],"shear":[{"curve":"stepped"},{"time":1,"curve":"stepped"},{"time":2}]},"bone22":{"rotate":[{"curve":"stepped"},{"time":1,"curve":"stepped"},{"time":2}],"translate":[{"curve":"stepped"},{"time":1,"curve":"stepped"},{"time":2}],"scale":[{"curve":"stepped"},{"time":1,"curve":"stepped"},{"time":2}],"shear":[{"curve":"stepped"},{"time":1,"curve":"stepped"},{"time":2}]},"bone23":{"rotate":[{"value":-0.7,"curve":"stepped"},{"time":1,"value":-0.7,"curve":"stepped"},{"time":2,"value":-0.7}],"translate":[{"curve":"stepped"},{"time":1,"curve":"stepped"},{"time":2}],"scale":[{"curve":"stepped"},{"time":1,"curve":"stepped"},{"time":2}],"shear":[{"curve":"stepped"},{"time":1,"curve":"stepped"},{"time":2}]},"bone24":{"rotate":[{"value":1.71,"curve":"stepped"},{"time":1,"value":1.71,"curve":"stepped"},{"time":2,"value":1.71}],"translate":[{"curve":"stepped"},{"time":1,"curve":"stepped"},{"time":2}],"scale":[{"curve":"stepped"},{"time":1,"curve":"stepped"},{"time":2}],"shear":[{"curve":"stepped"},{"time":1,"curve":"stepped"},{"time":2}]},"ikr":{"rotate":[{"curve":"stepped"},{"time":1,"curve":"stepped"},{"time":2}],"translate":[{"curve":"stepped"},{"time":1,"curve":"stepped"},{"time":2}],"scale":[{"curve":"stepped"},{"time":1,"curve":"stepped"},{"time":2}],"shear":[{"curve":"stepped"},{"time":1,"curve":"stepped"},{"time":2}]},"ikl":{"rotate":[{"curve":"stepped"},{"time":1,"curve":"stepped"},{"time":2}],"translate":[{"curve":"stepped"},{"time":1,"curve":"stepped"},{"time":2}],"scale":[{"curve":"stepped"},{"time":1,"curve":"stepped"},{"time":2}],"shear":[{"curve":"stepped"},{"time":1,"curve":"stepped"},{"time":2}]}}},"walk":{"bones":{"root":{"rotate":[{"curve":"stepped"},{"time":1}],"translate":[{"curve":"stepped"},{"time":1}],"scale":[{"curve":"stepped"},{"time":1}],"shear":[{"curve":"stepped"},{"time":1}]},"bone":{"rotate":[{"curve":"stepped"},{"time":1}],"translate":[{"curve":"stepped"},{"time":1}],"scale":[{"curve":"stepped"},{"time":1}],"shear":[{"curve":"stepped"},{"time":1}]},"bone2":{"rotate":[{"value":6.98,"curve":"stepped"},{"time":1,"value":6.98}],"translate":[{"curve":"stepped"},{"time":1}],"scale":[{"curve":"stepped"},{"time":1}],"shear":[{"curve":"stepped"},{"time":1}]},"bone3":{"rotate":[{"curve":"stepped"},{"time":1}],"translate":[{"curve":[0.167,0,0.333,-17.18,0.167,0,0.333,-0.16]},{"time":0.5,"x":-17.18,"y":-0.16,"curve":[0.667,-17.18,0.833,0,0.667,-0.16,0.833,0]},{"time":1}],"scale":[{"curve":"stepped"},{"time":1}],"shear":[{"curve":"stepped"},{"time":1}]},"bone4":{"rotate":[{"curve":"stepped"},{"time":1}],"translate":[{"curve":"stepped"},{"time":1}],"scale":[{"curve":"stepped"},{"time":1}],"shear":[{"curve":"stepped"},{"time":1}]},"bone5":{"rotate":[{"curve":"stepped"},{"time":1}],"translate":[{"curve":[0.167,0,0.333,-8.91,0.167,0,0.333,-1.04]},{"time":0.5,"x":-8.91,"y":-1.04,"curve":[0.667,-8.91,0.833,0,0.667,-1.04,0.833,0]},{"time":1}],"scale":[{"curve":"stepped"},{"time":1}],"shear":[{"curve":"stepped"},{"time":1}]},"bone6":{"rotate":[{"curve":"stepped"},{"time":1}],"translate":[{"curve":"stepped"},{"time":1}],"scale":[{"curve":"stepped"},{"time":1}],"shear":[{"curve":"stepped"},{"time":1}]},"bone7":{"rotate":[{"curve":"stepped"},{"time":1}],"translate":[{"y":6.05,"curve":"stepped"},{"time":1,"y":6.05}],"scale":[{"curve":"stepped"},{"time":1}],"shear":[{"curve":"stepped"},{"time":1}]},"bone8":{"rotate":[{"curve":"stepped"},{"time":1}],"translate":[{"y":7.49,"curve":"stepped"},{"time":1,"y":7.49}],"scale":[{"curve":"stepped"},{"time":1}],"shear":[{"curve":"stepped"},{"time":1}]},"bone9":{"rotate":[{"curve":"stepped"},{"time":1}],"translate":[{"x":8.99,"y":3.66,"curve":"stepped"},{"time":1,"x":8.99,"y":3.66}],"scale":[{"curve":"stepped"},{"time":1}],"shear":[{"curve":"stepped"},{"time":1}]},"bone10":{"rotate":[{"value":-15.05,"curve":[0.167,-15.05,0.333,-1.58]},{"time":0.5,"value":-1.58,"curve":[0.667,-1.58,0.833,-15.05]},{"time":1,"value":-15.05}],"translate":[{"x":11.99,"y":-0.02,"curve":"stepped"},{"time":1,"x":11.99,"y":-0.02}],"scale":[{"curve":"stepped"},{"time":1}],"shear":[{"curve":"stepped"},{"time":1}]},"bone11":{"rotate":[{"curve":"stepped"},{"time":1}],"translate":[{"curve":"stepped"},{"time":1}],"scale":[{"curve":"stepped"},{"time":1}],"shear":[{"curve":"stepped"},{"time":1}]},"bone12":{"rotate":[{"curve":"stepped"},{"time":1}],"translate":[{"curve":"stepped"},{"time":1}],"scale":[{"curve":"stepped"},{"time":1}],"shear":[{"curve":"stepped"},{"time":1}]},"bone13":{"rotate":[{"curve":"stepped"},{"time":1}],"translate":[{"curve":"stepped"},{"time":1}],"scale":[{"curve":"stepped"},{"time":1}],"shear":[{"curve":"stepped"},{"time":1}]},"bone14":{"rotate":[{"value":-7.08,"curve":[0.167,-7.08,0.333,5.46]},{"time":0.5,"value":5.46,"curve":[0.667,5.46,0.833,-7.08]},{"time":1,"value":-7.08}],"translate":[{"curve":"stepped"},{"time":1}],"scale":[{"curve":"stepped"},{"time":1}],"shear":[{"curve":"stepped"},{"time":1}]},"bone15":{"rotate":[{"curve":"stepped"},{"time":1}],"translate":[{"curve":"stepped"},{"time":1}],"scale":[{"curve":"stepped"},{"time":1}],"shear":[{"curve":"stepped"},{"time":1}]},"bone16":{"rotate":[{"curve":"stepped"},{"time":1}],"translate":[{"curve":"stepped"},{"time":1}],"scale":[{"curve":"stepped"},{"time":1}],"shear":[{"curve":"stepped"},{"time":1}]},"bone17":{"rotate":[{"curve":"stepped"},{"time":1}],"translate":[{"curve":"stepped"},{"time":1}],"scale":[{"curve":"stepped"},{"time":1}],"shear":[{"curve":"stepped"},{"time":1}]},"bone18":{"rotate":[{"curve":"stepped"},{"time":1}],"translate":[{"x":35.39,"y":49.39,"curve":[0.056,35.39,0.111,41.22,0.056,49.39,0.111,75.48]},{"time":0.1667,"x":38.14,"y":70.46,"curve":[0.222,35.07,0.278,32.65,0.222,65.44,0.278,29.18]},{"time":0.3333,"x":26.62,"y":15.41,"curve":[0.389,20.59,0.444,10.95,0.389,1.64,0.444,10.36]},{"time":0.5,"x":8,"y":6.24,"curve":[0.534,6.21,0.634,48.22,0.534,3.73,0.634,75.84]},{"time":0.6667,"x":49.46,"y":77.9,"curve":[0.745,52.31,0.756,7.29,0.745,82.62,0.756,13.88]},{"time":0.8333,"x":2.41,"y":4.32,"curve":[0.889,-1.07,0.945,35.39,0.889,-2.51,0.945,49.39]},{"time":1,"x":35.39,"y":49.39}],"scale":[{"curve":"stepped"},{"time":1}],"shear":[{"curve":"stepped"},{"time":1}]},"bone19":{"rotate":[{"curve":"stepped"},{"time":1}],"translate":[{"curve":"stepped"},{"time":1}],"scale":[{"curve":"stepped"},{"time":1}],"shear":[{"curve":"stepped"},{"time":1}]},"bone20":{"rotate":[{"curve":"stepped"},{"time":1}],"translate":[{"curve":[0.167,0,0.333,5.34,0.167,0,0.333,-32.1]},{"time":0.5,"x":5.34,"y":-32.1,"curve":[0.667,5.34,0.833,0,0.667,-32.1,0.833,0]},{"time":1}],"scale":[{"curve":"stepped"},{"time":1}],"shear":[{"curve":"stepped"},{"time":1}]},"bone21":{"rotate":[{"curve":"stepped"},{"time":1}],"translate":[{"curve":"stepped"},{"time":1}],"scale":[{"curve":"stepped"},{"time":1}],"shear":[{"curve":"stepped"},{"time":1}]},"bone22":{"rotate":[{"curve":"stepped"},{"time":1}],"translate":[{"curve":"stepped"},{"time":1}],"scale":[{"curve":"stepped"},{"time":1}],"shear":[{"curve":"stepped"},{"time":1}]},"bone23":{"rotate":[{"value":-0.7,"curve":"stepped"},{"time":1,"value":-0.7}],"translate":[{"curve":"stepped"},{"time":1}],"scale":[{"curve":"stepped"},{"time":1}],"shear":[{"curve":"stepped"},{"time":1}]},"bone24":{"rotate":[{"value":1.71,"curve":"stepped"},{"time":1,"value":1.71}],"translate":[{"curve":"stepped"},{"time":1}],"scale":[{"curve":"stepped"},{"time":1}],"shear":[{"curve":"stepped"},{"time":1}]},"ikr":{"rotate":[{"curve":"stepped"},{"time":1}],"translate":[{"x":6.13,"curve":[0.053,6.13,0.114,33.09,0.053,0,0.114,0]},{"time":0.1667,"x":44.05,"curve":[0.22,55,0.28,71.85,0.22,0,0.28,28.46]},{"time":0.3333,"x":71.85,"y":38.77,"curve":[0.386,71.85,0.447,42.69,0.386,49.08,0.447,61.84]},{"time":0.5,"x":31.74,"y":61.84,"curve":[0.503,31.17,0.611,-117.62,0.556,61.84,0.611,31.97]},{"time":0.6667,"x":-117.62,"y":31.97,"curve":[0.722,-117.62,0.778,-26.99,0.722,31.97,0.778,2.65]},{"time":0.8333,"x":-26.99,"y":2.65,"curve":[0.889,-26.99,0.944,6.13,0.889,2.65,0.944,0]},{"time":1,"x":6.13}],"scale":[{"curve":"stepped"},{"time":1}],"shear":[{"curve":"stepped"},{"time":1}]},"ikl":{"rotate":[{"curve":"stepped"},{"time":1}],"translate":[{"y":29.13,"curve":[0.053,0,0.114,-104.07,0.053,29.13,0.114,29.13]},{"time":0.1667,"x":-104.07,"y":29.04,"curve":[0.22,-104.07,0.28,-48.54,0.22,28.95,0.28,10.27]},{"time":0.3333,"x":-25.95,"y":4.34,"curve":[0.386,-3.35,0.447,31.5,0.386,-1.6,0.447,-6.58]},{"time":0.5,"x":31.5,"y":-6.58,"curve":[0.556,31.5,0.611,78.62,0.556,-6.58,0.611,-4.72]},{"time":0.6667,"x":78.62,"y":-4.72,"curve":[0.722,78.62,0.778,105.67,0.722,-4.72,0.778,74.52]},{"time":0.8333,"x":105.67,"y":74.52,"curve":[0.889,105.67,0.944,0,0.889,74.52,0.944,29.13]},{"time":1,"y":29.13}],"scale":[{"curve":"stepped"},{"time":1}],"shear":[{"curve":"stepped"},{"time":1}]}},"deform":{"default":{"body":{"body":[{"offset":82,"vertices":[-0.2811,5.71467,0,0,0,0,0.55101,14.70227,0.55135,14.7023,0.55124,14.7023,-0.80322,16.32757,-0.69464,16.33249,0.61249,16.33585,0.27565,7.35114,0.27565,7.35114,0.27563,7.35114,0.27564,7.35113,-0.53885,16.33842],"curve":"stepped"},{"time":1,"offset":82,"vertices":[-0.2811,5.71467,0,0,0,0,0.55101,14.70227,0.55135,14.7023,0.55124,14.7023,-0.80322,16.32757,-0.69464,16.33249,0.61249,16.33585,0.27565,7.35114,0.27565,7.35114,0.27563,7.35114,0.27564,7.35113,-0.53885,16.33842]}]}}}}}}